vcut/__init__.py
vcut/main.py
vcut/processor.py
vcut/transitions.py
vcut-0.0.3.dist-info/METADATA
vcut-0.0.3.dist-info/WHEEL
vcut-0.0.3.dist-info/entry_points.txt
vcut-0.0.3.dist-info/top_level.txt
vcut-0.0.3.dist-info/RECORD
