Metadata-Version: 2.4
Name: vcut
Version: 0.0.3
Summary: Video transition and splicing tool
Author-email: Casper <solitaryreach@gmail.com>
Keywords: mcp
Requires-Python: >=3.6
Requires-Dist: opencv-python>=4.5.0
Requires-Dist: numpy>=1.19.0
Requires-Dist: mcp[cli]>=1.6.0
Requires-Dist: twine>=6.1.0
Requires-Dist: build>=1.2.2.post1
